{
    "links": [
        {
            "source": "지상의 별처럼",
            "target": "우리들의 일그러진 영웅",
            "value": 3,
            "total": 1656,
            "same": 37
        },
        {
            "source": "나 홀로 집에 2 - 뉴욕을 헤매다",
            "target": "지상의 별처럼",
            "value": 3,
            "total": 2182,
            "same": 48
        },
        {
            "source": "바이센테니얼 맨",
            "target": "지상의 별처럼",
            "value": 3,
            "total": 2500,
            "same": 54
        },
        {
            "source": "아마데우스",
            "target": "지상의 별처럼",
            "value": 3,
            "total": 3321,
            "same": 70
        },
        {
            "source": "코러스",
            "target": "지상의 별처럼",
            "value": 3,
            "total": 3611,
            "same": 76
        },
        {
            "source": "지상의 별처럼",
            "target": "토이 스토리",
            "value": 3,
            "total": 1973,
            "same": 41
        },
        {
            "source": "아이 엠 샘",
            "target": "지상의 별처럼",
            "value": 3,
            "total": 3381,
            "same": 70
        },
        {
            "source": "블라인드 사이드",
            "target": "지상의 별처럼",
            "value": 3,
            "total": 4713,
            "same": 97
        },
        {
            "source": "지상의 별처럼",
            "target": "천공의 성 라퓨타",
            "value": 3,
            "total": 2012,
            "same": 41
        },
        {
            "source": "더 록",
            "target": "지상의 별처럼",
            "value": 2,
            "total": 2970,
            "same": 59
        },
        {
            "source": "울지마 톤즈",
            "target": "지상의 별처럼",
            "value": 2,
            "total": 4455,
            "same": 87
        },
        {
            "source": "지상의 별처럼",
            "target": "내 이름은 칸",
            "value": 2,
            "total": 5493,
            "same": 107
        },
        {
            "source": "집으로...",
            "target": "지상의 별처럼",
            "value": 2,
            "total": 2937,
            "same": 56
        },
        {
            "source": "빌리 엘리어트",
            "target": "지상의 별처럼",
            "value": 2,
            "total": 3625,
            "same": 69
        },
        {
            "source": "나 홀로 집에",
            "target": "지상의 별처럼",
            "value": 2,
            "total": 4151,
            "same": 79
        },
        {
            "source": "헬프",
            "target": "지상의 별처럼",
            "value": 2,
            "total": 3822,
            "same": 72
        }
    ],
    "nodes": [
        {
            "id": "나 홀로 집에",
            "group": 1,
            "href": "/movie/bi/mi/basic.nhn?code=10016",
            "genre": [
                "모험",
                "범죄",
                "가족",
                "코미디"
            ],
            "director": [
                "크리스 콜럼버스"
            ],
            "actor": [
                "맥컬리 컬킨",
                "조 페시",
                "다니엘 스턴"
            ]
        },
        {
            "id": "헬프",
            "group": 2,
            "href": "/movie/bi/mi/basic.nhn?code=82432",
            "genre": [
                "드라마"
            ],
            "director": [
                "테이트 테일러"
            ],
            "actor": [
                "엠마 스톤",
                "비올라 데이비스",
                "옥타비아 스펜서"
            ]
        },
        {
            "id": "아마데우스",
            "group": 2,
            "href": "/movie/bi/mi/basic.nhn?code=10114",
            "genre": [
                "드라마"
            ],
            "director": [
                "밀로스 포만"
            ],
            "actor": [
                "톰 헐스",
                "F. 머레이 아브라함",
                "엘리자베스 베리지"
            ]
        },
        {
            "id": "집으로...",
            "group": 2,
            "href": "/movie/bi/mi/basic.nhn?code=34324",
            "genre": [
                "드라마",
                "가족"
            ],
            "director": [
                "이정향"
            ],
            "actor": [
                "김을분",
                "유승호"
            ]
        },
        {
            "id": "울지마 톤즈",
            "group": 3,
            "href": "/movie/bi/mi/basic.nhn?code=76667",
            "genre": [
                "다큐멘터리"
            ],
            "director": [
                "구수환"
            ],
            "actor": [
                "이금희",
                "이태석"
            ]
        },
        {
            "id": "더 록",
            "group": 4,
            "href": "/movie/bi/mi/basic.nhn?code=17135",
            "genre": [
                "액션"
            ],
            "director": [
                "마이클 베이"
            ],
            "actor": [
                "숀 코네리",
                "니콜라스 케이지",
                "에드 해리스"
            ]
        },
        {
            "id": "아이 엠 샘",
            "group": 2,
            "href": "/movie/bi/mi/basic.nhn?code=34227",
            "genre": [
                "드라마"
            ],
            "director": [
                "제시 넬슨"
            ],
            "actor": [
                "숀 펜",
                "미셸 파이퍼"
            ]
        },
        {
            "id": "코러스",
            "group": 2,
            "href": "/movie/bi/mi/basic.nhn?code=39584",
            "genre": [
                "드라마"
            ],
            "director": [
                "크리스토퍼 파라티에"
            ],
            "actor": [
                "제라르 쥐노",
                "프랑수와 벨레앙",
                "장 밥티스트 모니에"
            ]
        },
        {
            "id": "빌리 엘리어트",
            "group": 2,
            "href": "/movie/bi/mi/basic.nhn?code=31013",
            "genre": [
                "드라마",
                "가족",
                "코미디"
            ],
            "director": [
                "스티븐 달드리"
            ],
            "actor": [
                "제이미 벨",
                "줄리 월터스",
                "게리 루이스"
            ]
        },
        {
            "id": "나 홀로 집에 2 - 뉴욕을 헤매다",
            "group": 1,
            "href": "/movie/bi/mi/basic.nhn?code=12270",
            "genre": [
                "모험",
                "액션",
                "범죄",
                "스릴러",
                "코미디",
                "가족"
            ],
            "director": [
                "크리스 콜럼버스"
            ],
            "actor": [
                "맥컬리 컬킨",
                "조 페시",
                "다니엘 스턴"
            ]
        },
        {
            "id": "바이센테니얼 맨",
            "group": 5,
            "href": "/movie/bi/mi/basic.nhn?code=28788",
            "genre": [
                "SF",
                "드라마"
            ],
            "director": [
                "크리스 콜럼버스"
            ],
            "actor": [
                "로빈 윌리엄스"
            ]
        },
        {
            "id": "블라인드 사이드",
            "group": 2,
            "href": "/movie/bi/mi/basic.nhn?code=71081",
            "genre": [
                "드라마"
            ],
            "director": [
                "존 리 행콕"
            ],
            "actor": [
                "산드라 블록"
            ]
        },
        {
            "id": "지상의 별처럼",
            "group": 2,
            "href": "/movie/bi/mi/basic.nhn?code=51172",
            "genre": [
                "드라마"
            ],
            "director": [
                "아미르 칸",
                "아몰 굽테"
            ],
            "actor": [
                "다쉴 사페리",
                "아미르 칸"
            ]
        },
        {
            "id": "우리들의 일그러진 영웅",
            "group": 2,
            "href": "/movie/bi/mi/basic.nhn?code=12297",
            "genre": [
                "드라마"
            ],
            "director": [
                "박종원"
            ],
            "actor": [
                "홍경인",
                "고정일",
                "최민식"
            ]
        },
        {
            "id": "토이 스토리",
            "group": 6,
            "href": "/movie/bi/mi/basic.nhn?code=17153",
            "genre": [
                "애니메이션",
                "코미디",
                "가족",
                "판타지"
            ],
            "director": [
                "존 라세터"
            ],
            "actor": [
                "톰 행크스",
                "팀 알렌"
            ]
        },
        {
            "id": "천공의 성 라퓨타",
            "group": 6,
            "href": "/movie/bi/mi/basic.nhn?code=18782",
            "genre": [
                "애니메이션",
                "판타지",
                "모험"
            ],
            "director": [
                "미야자키 하야오"
            ],
            "actor": [
                "타나카 마유미",
                "요코자와 케이코",
                "하츠이 코토에"
            ]
        },
        {
            "id": "내 이름은 칸",
            "group": 2,
            "href": "/movie/bi/mi/basic.nhn?code=70651",
            "genre": [
                "드라마"
            ],
            "director": [
                "카란 조하르"
            ],
            "actor": [
                "샤룩 칸",
                "까졸"
            ]
        }
    ],
    "genre_data": [
        {
            "title": "모험",
            "group": 1
        },
        {
            "title": "드라마",
            "group": 2
        },
        {
            "title": "다큐멘터리",
            "group": 3
        },
        {
            "title": "액션",
            "group": 4
        },
        {
            "title": "SF",
            "group": 5
        },
        {
            "title": "애니메이션",
            "group": 6
        }
    ],
    "data": [
        {
            "movie_n": 101,
            "genre_n": 6
        }
    ]
}